gameconcept_analyzer/__init__.py
gameconcept_analyzer/main.py
gameconcept_analyzer/prompts.py
gameconcept_analyzer-2025.12.21143849.dist-info/METADATA
gameconcept_analyzer-2025.12.21143849.dist-info/WHEEL
gameconcept_analyzer-2025.12.21143849.dist-info/top_level.txt
gameconcept_analyzer-2025.12.21143849.dist-info/RECORD
