Metadata-Version: 2.4
Name: gameconcept-analyzer
Version: 2025.12.21143849
Summary: A new package that processes user-submitted text descriptions of local multiplayer party game concepts and returns structured feedback or suggestions. It helps game developers or enthusiasts by analyz
Author-email: gameconcept-analyzer <hi@eugene.plus>
License: MIT
Project-URL: Homepage, https://github.com/chigwell/gameconcept-analyzer
Requires-Python: >=3.9
Requires-Dist: langchain-llm7>=0.0.0
Requires-Dist: llmatch-messages>=0.0.0
Requires-Dist: langchain-core>=0.3.0
